FPGA/vgs_controller.v
module vgs_controller (
    input wire clk,
    input wire rst_n,              
    input wire InVGS,
    output reg OutVGS,
    output reg FlybackVGS
);

reg rising_edge_detected;         // Flag to track InVGS rising edge
reg falling_edge_detected;        // Flag to track falling edge for sequencing

// Handle positive edge of clock
always @(posedge clk or negedge rst_n) begin
    if (!rst_n) begin
        FlybackVGS <= 1;          // Default state is high
        rising_edge_detected <= 0;
        falling_edge_detected <= 0;
    end else begin
        if (InVGS) begin
            if (!rising_edge_detected) begin
                // InVGS just went high
                FlybackVGS <= 0;
                rising_edge_detected <= 1;
                falling_edge_detected <= 0;
            end
        end else begin  // InVGS is low
            rising_edge_detected <= 0;
            if (OutVGS) begin
                // OutVGS is high, do normal turn-off sequence
                FlybackVGS <= 1;  // FlybackVGS goes high first
                falling_edge_detected <= 1;  // Signal for OutVGS to go low on next negedge
            end else if (!FlybackVGS && !falling_edge_detected) begin
                // Short pulse case: OutVGS never went high
                FlybackVGS <= 1;  // Return FlybackVGS to high
                falling_edge_detected <= 0;
            end
        end
    end
end

// Handle negative edge of clock
always @(negedge clk or negedge rst_n) begin
    if (!rst_n) begin
        OutVGS <= 0;
    end else begin
        if (InVGS && rising_edge_detected) begin
            OutVGS <= 1;  // OutVGS goes high half clock after InVGS
        end else if (falling_edge_detected) begin
            OutVGS <= 0;  // OutVGS goes low half a clock after FlybackVGS went high
        end
    end
end

endmodule

FPGA/vgs_controller_tb.v
`timescale 1ns/1ps

module vgs_controller_tb;

    // Test bench signals
    reg clk;
    reg rst_n;
    reg InVGS;
    wire OutVGS;
    wire FlybackVGS;
    
    // Clock generation parameters
    parameter CLK_PERIOD = 83.33; // 12MHz = 83.33ns period
    
    // Test case parameters
    parameter TEST_DELAY = 20;    // Standard delay between tests (cycles)
    
    // Instantiate the VGS controller
    vgs_controller uut (
        .clk(clk),
        .rst_n(rst_n),
        .InVGS(InVGS),
        .OutVGS(OutVGS),
        .FlybackVGS(FlybackVGS)
    );
    
    // Clock generation
    always begin
        clk = 0;
        #(CLK_PERIOD/2);
        clk = 1;
        #(CLK_PERIOD/2);
    end

    // Task for standard delay between tests
    task wait_cycles;
        input integer cycles;
        begin
            repeat(cycles) @(posedge clk);
        end
    endtask

    // Task to create a glitch on InVGS
    task glitch;
        input integer low_cycles;  // How many cycles InVGS stays low
        begin
            InVGS = 0;
            wait_cycles(low_cycles);
            InVGS = 1;
        end
    endtask
    
    // Test stimulus
    initial begin
        // Set up waveform dumping
        $dumpfile("vgs_controller_tb.vcd");
        $dumpvars(0, vgs_controller_tb);
        
        // Test case descriptions for waveform viewing
        $display("\n=== VGS Controller Comprehensive Test Cases ===\n");
        $display("Test 1: Basic reset and initialization");
        $display("Test 2: Normal operation with various pulse widths");
        $display("Test 3: Short pulses (edge cases)");
        $display("Test 4: EMI immunity testing");
        $display("Test 5: Rapid switching test");
        $display("\n============================================\n");

        // Initialize signals
        rst_n = 0;
        InVGS = 0;
        
        // Test 1: Reset and Initialization
        $display("Starting Test 1: Reset and Initialization");
        wait_cycles(5);
        rst_n = 1;
        wait_cycles(5);
        
        // Test 2: Normal Operation with Various Pulse Widths
        $display("Starting Test 2: Normal Operation Tests");
        
        // 2a: Medium pulse (10 cycles)
        $display("Test 2a: Medium pulse (10 cycles)");
        InVGS = 1;
        wait_cycles(10);
        InVGS = 0;
        wait_cycles(TEST_DELAY);
        
        // 2b: Long pulse (20 cycles)
        $display("Test 2b: Long pulse (20 cycles)");
        InVGS = 1;
        wait_cycles(20);
        InVGS = 0;
        wait_cycles(TEST_DELAY);
        
        // Test 3: Short Pulse Edge Cases
        $display("Starting Test 3: Short Pulse Tests");
        
        // 3a: Pulse too short for OutVGS (1 cycle)
        $display("Test 3a: 1-cycle pulse");
        InVGS = 1;
        wait_cycles(1);
        InVGS = 0;
        wait_cycles(TEST_DELAY);
        
        // 3b: Pulse just short of OutVGS threshold (2 cycles)
        $display("Test 3b: 2-cycle pulse");
        InVGS = 1;
        wait_cycles(2);
        InVGS = 0;
        wait_cycles(TEST_DELAY);
        
        // 3c: Pulse exactly at OutVGS threshold (3 cycles)
        $display("Test 3c: 3-cycle pulse");
        InVGS = 1;
        wait_cycles(3);
        InVGS = 0;
        wait_cycles(TEST_DELAY);
        
        // Test 4: EMI Immunity Testing
        $display("Starting Test 4: EMI Immunity Tests");
        
        // 4a: Single-cycle glitch during high state
        $display("Test 4a: Single-cycle glitch");
        InVGS = 1;
        wait_cycles(5);  // Establish normal operation
        glitch(1);      // 1-cycle low glitch
        wait_cycles(5);
        InVGS = 0;
        wait_cycles(TEST_DELAY);
        
        // 4b: Two-cycle glitch during high state
        $display("Test 4b: Two-cycle glitch");
        InVGS = 1;
        wait_cycles(5);
        glitch(2);      // 2-cycle low glitch
        wait_cycles(5);
        InVGS = 0;
        wait_cycles(TEST_DELAY);
        
        // 4c: Multiple glitches
        $display("Test 4c: Multiple glitches");
        InVGS = 1;
        wait_cycles(5);
        glitch(1);
        wait_cycles(3);
        glitch(2);
        wait_cycles(5);
        InVGS = 0;
        wait_cycles(TEST_DELAY);
        
        // Test 5: Rapid Switching
        $display("Starting Test 5: Rapid Switching Test");
        repeat(5) begin
            InVGS = 1;
            wait_cycles(4);
            InVGS = 0;
            wait_cycles(4);
        end
        wait_cycles(TEST_DELAY);
        
        // End simulation
        $display("\nSimulation complete!");
        $finish;
    end
    
    // Monitor changes and timing
    reg [63:0] last_change_time;
    initial begin
        last_change_time = 0;
        forever @(OutVGS or FlybackVGS) begin
            if ($time != last_change_time) begin
                $display("Time=%0t: OutVGS=%b FlybackVGS=%b InVGS=%b",
                         $time, OutVGS, FlybackVGS, InVGS);
                last_change_time = $time;
            end
        end
    end

endmodule

FPGA/vgs_controller_tb.vcd
$date
	Mon Jan 13 15:22:20 2025
$end
$version
	Icarus Verilog
$end
$timescale
	1ps
$end
$scope module vgs_controller_tb $end
$var wire 1 ! OutVGS $end
$var wire 1 " FlybackVGS $end
$var reg 1 # InVGS $end
$var reg 1 $ clk $end
$var reg 64 % last_change_time [63:0] $end
$var reg 1 & rst_n $end
$scope module uut $end
$var wire 1 # InVGS $end
$var wire 1 $ clk $end
$var wire 1 & rst_n $end
$var reg 1 " FlybackVGS $end
$var reg 1 ! OutVGS $end
$var reg 1 ' falling_edge_detected $end
$var reg 1 ( rising_edge_detected $end
$upscope $end
$scope task glitch $end
$var integer 32 ) low_cycles [31:0] $end
$upscope $end
$scope task wait_cycles $end
$var integer 32 * cycles [31:0] $end
$upscope $end
$upscope $end
$enddefinitions $end
#0
$dumpvars
b101 *
bx )
0(
0'
0&
b0 %
0$
0#
1"
0!
$end
#41665
1$
#83330
0$
#124995
1$
#166660
0$
#208325
1$
#249990
0$
#291655
1$
#333320
0$
#374985
1&
1$
#416650
0$
#458315
1$
#499980
0$
#541645
1$
#583310
0$
#624975
1$
#666640
0$
#708305
1$
#749970
0$
#791635
b1100011000 %
1(
0"
b1010 *
1#
1$
#833300
b1101000001 %
1!
0$
#874965
1$
#916630
0$
#958295
1$
#999960
0$
#1041625
1$
#1083290
0$
#1124955
1$
#1166620
0$
#1208285
1$
#1249950
0$
#1291615
1$
#1333280
0$
#1374945
1$
#1416610
0$
#1458275
1$
#1499940
0$
#1541605
1$
#1583270
0$
#1624935
b11001011001 %
1'
1"
0(
b10100 *
0#
1$
#1666600
b11010000011 %
0!
0$
#1708265
1$
#1749930
0$
#1791595
1$
#1833260
0$
#1874925
1$
#1916590
0$
#1958255
1$
#1999920
0$
#2041585
1$
#2083250
0$
#2124915
1$
#2166580
0$
#2208245
1$
#2249910
0$
#2291575
1$
#2333240
0$
#2374905
1$
#2416570
0$
#2458235
1$
#2499900
0$
#2541565
1$
#2583230
0$
#2624895
1$
#2666560
0$
#2708225
1$
#2749890
0$
#2791555
1$
#2833220
0$
#2874885
1$
#2916550
0$
#2958215
1$
#2999880
0$
#3041545
1$
#3083210
0$
#3124875
1$
#3166540
0$
#3208205
1$
#3249870
0$
#3291535
b110011011100 %
0'
1(
0"
1#
1$
#3333200
b110100000101 %
1!
0$
#3374865
1$
#3416530
0$
#3458195
1$
#3499860
0$
#3541525
1$
#3583190
0$
#3624855
1$
#3666520
0$
#3708185
1$
#3749850
0$
#3791515
1$
#3833180
0$
#3874845
1$
#3916510
0$
#3958175
1$
#3999840
0$
#4041505
1$
#4083170
0$
#4124835
1$
#4166500
0$
#4208165
1$
#4249830
0$
#4291495
1$
#4333160
0$
#4374825
1$
#4416490
0$
#4458155
1$
#4499820
0$
#4541485
1$
#4583150
0$
#4624815
1$
#4666480
0$
#4708145
1$
#4749810
0$
#4791475
1$
#4833140
0$
#4874805
1$
#4916470
0$
#4958135
b1001101011110 %
1'
1"
0(
0#
1$
#4999800
b1001110001000 %
0!
0$
#5041465
1$
#5083130
0$
#5124795
1$
#5166460
0$
#5208125
1$
#5249790
0$
#5291455
1$
#5333120
0$
#5374785
1$
#5416450
0$
#5458115
1$
#5499780
0$
#5541445
1$
#5583110
0$
#5624775
1$
#5666440
0$
#5708105
1$
#5749770
0$
#5791435
1$
#5833100
0$
#5874765
1$
#5916430
0$
#5958095
1$
#5999760
0$
#6041425
1$
#6083090
0$
#6124755
1$
#6166420
0$
#6208085
1$
#6249750
0$
#6291415
1$
#6333080
0$
#6374745
1$
#6416410
0$
#6458075
1$
#6499740
0$
#6541405
1$
#6583070
0$
#6624735
b1100111100001 %
0'
1(
0"
b1 *
1#
1$
#6666400
b1101000001010 %
1!
0$
#6708065
b1101000110100 %
1'
1"
0(
b10100 *
0#
1$
#6749730
b1101001011110 %
0!
0$
#6791395
1$
#6833060
0$
#6874725
1$
#6916390
0$
#6958055
1$
#6999720
0$
#7041385
1$
#7083050
0$
#7124715
1$
#7166380
0$
#7208045
1$
#7249710
0$
#7291375
1$
#7333040
0$
#7374705
1$
#7416370
0$
#7458035
1$
#7499700
0$
#7541365
1$
#7583030
0$
#7624695
1$
#7666360
0$
#7708025
1$
#7749690
0$
#7791355
1$
#7833020
0$
#7874685
1$
#7916350
0$
#7958015
1$
#7999680
0$
#8041345
1$
#8083010
0$
#8124675
1$
#8166340
0$
#8208005
1$
#8249670
0$
#8291335
1$
#8333000
0$
#8374665
b10000010110111 %
0'
1(
0"
b10 *
1#
1$
#8416330
b10000011100000 %
1!
0$
#8457995
1$
#8499660
0$
#8541325
b10000101011101 %
1'
1"
0(
b10100 *
0#
1$
#8582990
b10000110000111 %
0!
0$
#8624655
1$
#8666320
0$
#8707985
1$
#8749650
0$
#8791315
1$
#8832980
0$
#8874645
1$
#8916310
0$
#8957975
1$
#8999640
0$
#9041305
1$
#9082970
0$
#9124635
1$
#9166300
0$
#9207965
1$
#9249630
0$
#9291295
1$
#9332960
0$
#9374625
1$
#9416290
0$
#9457955
1$
#9499620
0$
#9541285
1$
#9582950
0$
#9624615
1$
#9666280
0$
#9707945
1$
#9749610
0$
#9791275
1$
#9832940
0$
#9874605
1$
#9916270
0$
#9957935
1$
#9999600
0$
#10041265
1$
#10082930
0$
#10124595
1$
#10166260
0$
#10207925
b10011111100000 %
0'
1(
0"
b11 *
1#
1$
#10249590
b10100000001010 %
1!
0$
#10291255
1$
#10332920
0$
#10374585
1$
#10416250
0$
#10457915
b10100011011010 %
1'
1"
0(
b10100 *
0#
1$
#10499580
b10100100000100 %
0!
0$
#10541245
1$
#10582910
0$
#10624575
1$
#10666240
0$
#10707905
1$
#10749570
0$
#10791235
1$
#10832900
0$
#10874565
1$
#10916230
0$
#10957895
1$
#10999560
0$
#11041225
1$
#11082890
0$
#11124555
1$
#11166220
0$
#11207885
1$
#11249550
0$
#11291215
1$
#11332880
0$
#11374545
1$
#11416210
0$
#11457875
1$
#11499540
0$
#11541205
1$
#11582870
0$
#11624535
1$
#11666200
0$
#11707865
1$
#11749530
0$
#11791195
1$
#11832860
0$
#11874525
1$
#11916190
0$
#11957855
1$
#11999520
0$
#12041185
1$
#12082850
0$
#12124515
b10111101011101 %
0'
1(
0"
b101 *
1#
1$
#12166180
b10111110000110 %
1!
0$
#12207845
1$
#12249510
0$
#12291175
1$
#12332840
0$
#12374505
1$
#12416170
0$
#12457835
1$
#12499500
0$
#12541165
b11000011111101 %
1'
1"
0(
b1 *
0#
b1 )
1$
#12582830
b11000100100111 %
0!
0$
#12624495
b11000101010000 %
0'
1(
0"
b101 *
1#
1$
#12666160
b11000101111010 %
1!
0$
#12707825
1$
#12749490
0$
#12791155
1$
#12832820
0$
#12874485
1$
#12916150
0$
#12957815
1$
#12999480
0$
#13041145
b11001011110001 %
1'
1"
0(
b10100 *
0#
1$
#13082810
b11001100011011 %
0!
0$
#13124475
1$
#13166140
0$
#13207805
1$
#13249470
0$
#13291135
1$
#13332800
0$
#13374465
1$
#13416130
0$
#13457795
1$
#13499460
0$
#13541125
1$
#13582790
0$
#13624455
1$
#13666120
0$
#13707785
1$
#13749450
0$
#13791115
1$
#13832780
0$
#13874445
1$
#13916110
0$
#13957775
1$
#13999440
0$
#14041105
1$
#14082770
0$
#14124435
1$
#14166100
0$
#14207765
1$
#14249430
0$
#14291095
1$
#14332760
0$
#14374425
1$
#14416090
0$
#14457755
1$
#14499420
0$
#14541085
1$
#14582750
0$
#14624415
1$
#14666080
0$
#14707745
b11100101110100 %
0'
1(
0"
b101 *
1#
1$
#14749410
b11100110011101 %
1!
0$
#14791075
1$
#14832740
0$
#14874405
1$
#14916070
0$
#14957735
1$
#14999400
0$
#15041065
1$
#15082730
0$
#15124395
b11101100010100 %
1'
1"
0(
b10 *
0#
b10 )
1$
#15166060
b11101100111110 %
0!
0$
#15207725
1$
#15249390
0$
#15291055
b11101110111011 %
0'
1(
0"
b101 *
1#
1$
#15332720
b11101111100101 %
1!
0$
#15374385
1$
#15416050
0$
#15457715
1$
#15499380
0$
#15541045
1$
#15582710
0$
#15624375
1$
#15666040
0$
#15707705
b11110101011100 %
1'
1"
0(
b10100 *
0#
1$
#15749370
b11110110000101 %
0!
0$
#15791035
1$
#15832700
0$
#15874365
1$
#15916030
0$
#15957695
1$
#15999360
0$
#16041025
1$
#16082690
0$
#16124355
1$
#16166020
0$
#16207685
1$
#16249350
0$
#16291015
1$
#16332680
0$
#16374345
1$
#16416010
0$
#16457675
1$
#16499340
0$
#16541005
1$
#16582670
0$
#16624335
1$
#16666000
0$
#16707665
1$
#16749330
0$
#16790995
1$
#16832660
0$
#16874325
1$
#16915990
0$
#16957655
1$
#16999320
0$
#17040985
1$
#17082650
0$
#17124315
1$
#17165980
0$
#17207645
1$
#17249310
0$
#17290975
1$
#17332640
0$
#17374305
b100001111011110 %
0'
1(
0"
b101 *
1#
1$
#17415970
b100010000001000 %
1!
0$
#17457635
1$
#17499300
0$
#17540965
1$
#17582630
0$
#17624295
1$
#17665960
0$
#17707625
1$
#17749290
0$
#17790955
b100010101111111 %
1'
1"
0(
b1 *
0#
b1 )
1$
#17832620
b100010110101001 %
0!
0$
#17874285
b100010111010010 %
0'
1(
0"
b11 *
1#
1$
#17915950
b100010111111100 %
1!
0$
#17957615
1$
#17999280
0$
#18040945
1$
#18082610
0$
#18124275
b100011011001100 %
1'
1"
0(
b10 *
0#
b10 )
1$
#18165940
b100011011110110 %
0!
0$
#18207605
1$
#18249270
0$
#18290935
b100011101110011 %
0'
1(
0"
b101 *
1#
1$
#18332600
b100011110011101 %
1!
0$
#18374265
1$
#18415930
0$
#18457595
1$
#18499260
0$
#18540925
1$
#18582590
0$
#18624255
1$
#18665920
0$
#18707585
b100100100010100 %
1'
1"
0(
b10100 *
0#
1$
#18749250
b100100100111101 %
0!
0$
#18790915
1$
#18832580
0$
#18874245
1$
#18915910
0$
#18957575
1$
#18999240
0$
#19040905
1$
#19082570
0$
#19124235
1$
#19165900
0$
#19207565
1$
#19249230
0$
#19290895
1$
#19332560
0$
#19374225
1$
#19415890
0$
#19457555
1$
#19499220
0$
#19540885
1$
#19582550
0$
#19624215
1$
#19665880
0$
#19707545
1$
#19749210
0$
#19790875
1$
#19832540
0$
#19874205
1$
#19915870
0$
#19957535
1$
#19999200
0$
#20040865
1$
#20082530
0$
#20124195
1$
#20165860
0$
#20207525
1$
#20249190
0$
#20290855
1$
#20332520
0$
#20374185
b100111110010110 %
0'
1(
0"
b100 *
1#
1$
#20415850
b100111111000000 %
1!
0$
#20457515
1$
#20499180
0$
#20540845
1$
#20582510
0$
#20624175
1$
#20665840
0$
#20707505
b101000011100100 %
1'
1"
0(
0#
1$
#20749170
b101000100001101 %
0!
0$
#20790835
1$
#20832500
0$
#20874165
1$
#20915830
0$
#20957495
1$
#20999160
0$
#21040825
b101001000110001 %
0'
1(
0"
1#
1$
#21082490
b101001001011010 %
1!
0$
#21124155
1$
#21165820
0$
#21207485
1$
#21249150
0$
#21290815
1$
#21332480
0$
#21374145
b101001101111110 %
1'
1"
0(
0#
1$
#21415810
b101001110101000 %
0!
0$
#21457475
1$
#21499140
0$
#21540805
1$
#21582470
0$
#21624135
1$
#21665800
0$
#21707465
b101010011001011 %
0'
1(
0"
1#
1$
#21749130
b101010011110101 %
1!
0$
#21790795
1$
#21832460
0$
#21874125
1$
#21915790
0$
#21957455
1$
#21999120
0$
#22040785
b101011000011001 %
1'
1"
0(
0#
1$
#22082450
b101011001000010 %
0!
0$
#22124115
1$
#22165780
0$
#22207445
1$
#22249110
0$
#22290775
1$
#22332440
0$
#22374105
b101011101100110 %
0'
1(
0"
1#
1$
#22415770
b101011110010000 %
1!
0$
#22457435
1$
#22499100
0$
#22540765
1$
#22582430
0$
#22624095
1$
#22665760
0$
#22707425
b101100010110011 %
1'
1"
0(
0#
1$
#22749090
b101100011011101 %
0!
0$
#22790755
1$
#22832420
0$
#22874085
1$
#22915750
0$
#22957415
1$
#22999080
0$
#23040745
b101101000000001 %
0'
1(
0"
1#
1$
#23082410
b101101000101010 %
1!
0$
#23124075
1$
#23165740
0$
#23207405
1$
#23249070
0$
#23290735
1$
#23332400
0$
#23374065
b101101101001110 %
1'
1"
0(
0#
1$
#23415730
b101101101111000 %
0!
0$
#23457395
1$
#23499060
0$
#23540725
1$
#23582390
0$
#23624055
1$
#23665720
0$
#23707385
b10100 *
1$
